{"STABLE":{"clips":905,"clipViews":475853,"hoursLive":96.1},"PLAQUE":{"clips":940,"clipViews":245167,"hoursLive":41},"WEEN":{"clips":922,"clipViews":284026,"hoursLive":100.1},"SKETCH":{"clips":838,"clipViews":28349,"hoursLive":48.9},"LACY":{"clips":907,"clipViews":433423,"hoursLive":105.8},"MARLON":{"clips":962,"clipViews":228892,"hoursLive":97.5},"SILKY":{"clips":972,"clipViews":110885,"hoursLive":98.6},"DRUM":{"clips":201,"clipViews":7922,"hoursLive":52.9},"CGC":{"clips":0,"clipViews":0,"hoursLive":0},"YUSUF":{"clips":944,"clipViews":15876,"hoursLive":99.5},"PINK":{"clips":206,"clipViews":11181,"hoursLive":109.1},"MOOK":{"clips":443,"clipViews":22249,"hoursLive":64.3},"AIKOOO":{"clips":237,"clipViews":840,"hoursLive":65.9},"STRAIG":{"clips":0,"clipViews":0,"hoursLive":0},"COOLBU":{"clips":63,"clipViews":1600,"hoursLive":92.9},"A2GUAP":{"clips":278,"clipViews":9183,"hoursLive":76.1},"AVAZUR":{"clips":98,"clipViews":8123,"hoursLive":65},"2XCEEE":{"clips":273,"clipViews":7864,"hoursLive":43.3},"ANDREW":{"clips":420,"clipViews":3422,"hoursLive":48.3},"ANGELC":{"clips":118,"clipViews":21234,"hoursLive":22.3},"AOZAMI":{"clips":382,"clipViews":21135,"hoursLive":104},"BENJYC":{"clips":922,"clipViews":39627,"hoursLive":83.6},"BLAZIA":{"clips":726,"clipViews":6874,"hoursLive":47.2},"BONITA":{"clips":288,"clipViews":5173,"hoursLive":63.9},"BRAEDE":{"clips":938,"clipViews":100939,"hoursLive":101.1},"GIOVAN":{"clips":0,"clipViews":0,"hoursLive":0},"MADAIC":{"clips":47,"clipViews":1084,"hoursLive":76},"MADI2H":{"clips":904,"clipViews":283206,"hoursLive":88.2},"MALEK0":{"clips":400,"clipViews":31116,"hoursLive":106.9},"MANDOO":{"clips":134,"clipViews":1663,"hoursLive":95.8},"MEESTE":{"clips":949,"clipViews":83204,"hoursLive":109.4},"MIYA":{"clips":0,"clipViews":0,"hoursLive":0},"MYANIC":{"clips":0,"clipViews":0,"hoursLive":0},"NOEMI":{"clips":200,"clipViews":13091,"hoursLive":99.7},"NOTBIL":{"clips":923,"clipViews":211845,"hoursLive":72},"ONLYLA":{"clips":740,"clipViews":51476,"hoursLive":49.2},"PAYTON":{"clips":0,"clipViews":0,"hoursLive":0},"PUDGIE":{"clips":507,"clipViews":20174,"hoursLive":43.4},"REEMKN":{"clips":929,"clipViews":119593,"hoursLive":56.6},"RIZPY":{"clips":755,"clipViews":29520,"hoursLive":38.5},"RULAEM":{"clips":252,"clipViews":3846,"hoursLive":34.2},"RUNIK":{"clips":0,"clipViews":0,"hoursLive":0},"SARAHF":{"clips":256,"clipViews":8464,"hoursLive":68.7},"SELEOL":{"clips":350,"clipViews":4123,"hoursLive":63.5},"SHAZDE":{"clips":851,"clipViews":27553,"hoursLive":69.6},"SIERRA":{"clips":893,"clipViews":54248,"hoursLive":105.7},"SUHMMI":{"clips":579,"clipViews":13379,"hoursLive":75.7},"SUKIIM":{"clips":949,"clipViews":158087,"hoursLive":91.5},"SUBURB":{"clips":862,"clipViews":377012,"hoursLive":87.7},"TAYLOR":{"clips":0,"clipViews":0,"hoursLive":0},"YSABEL":{"clips":542,"clipViews":4310,"hoursLive":95.5},"COOLIT":{"clips":143,"clipViews":1733,"hoursLive":59.3},"CUTEGU":{"clips":297,"clipViews":1954,"hoursLive":101.5},"DAMIIL":{"clips":842,"clipViews":20135,"hoursLive":86.6},"DOPEBO":{"clips":173,"clipViews":2043,"hoursLive":50.6},"E11YSA":{"clips":959,"clipViews":64549,"hoursLive":80.2},"ELINAM":{"clips":284,"clipViews":8057,"hoursLive":103.6},"EZEE":{"clips":935,"clipViews":14298,"hoursLive":100.3},"FLAKO":{"clips":226,"clipViews":7370,"hoursLive":111.6},"FUMIBE":{"clips":142,"clipViews":12323,"hoursLive":78},"FTGIOO":{"clips":953,"clipViews":65030,"hoursLive":21.9},"ILIKEH":{"clips":920,"clipViews":629385,"hoursLive":54.7},"SHONYX":{"clips":0,"clipViews":0,"hoursLive":0},"CINNAM":{"clips":0,"clipViews":0,"hoursLive":0},"THATSD":{"clips":727,"clipViews":44006,"hoursLive":81.6},"IWASTO":{"clips":226,"clipViews":2137,"hoursLive":97.9},"JADAMA":{"clips":470,"clipViews":14364,"hoursLive":63.8},"JAYMOM":{"clips":812,"clipViews":46129,"hoursLive":94.6},"JSHOCK":{"clips":923,"clipViews":40744,"hoursLive":104.5},"JORDYN":{"clips":955,"clipViews":142804,"hoursLive":77.9},"JUICYJ":{"clips":909,"clipViews":35920,"hoursLive":89.7},"KICOSM":{"clips":69,"clipViews":11333,"hoursLive":31.4},"KIIING":{"clips":221,"clipViews":3766,"hoursLive":11.9},"KING68":{"clips":576,"clipViews":8862,"hoursLive":74.8},"THEMIG":{"clips":158,"clipViews":8115,"hoursLive":37.4},"THEREA":{"clips":422,"clipViews":14791,"hoursLive":77.5},"LEII":{"clips":0,"clipViews":0,"hoursLive":0},"TIANAM":{"clips":0,"clipViews":0,"hoursLive":0},"WABEWR":{"clips":75,"clipViews":2278,"hoursLive":86.4},"WARDRO":{"clips":892,"clipViews":86795,"hoursLive":48.1},"WRLDKA":{"clips":289,"clipViews":9327,"hoursLive":97.1},"XSCAPE":{"clips":56,"clipViews":9345,"hoursLive":18.1},"YABOYY":{"clips":0,"clipViews":0,"hoursLive":0},"YUGI2X":{"clips":969,"clipViews":40560,"hoursLive":106.1},"STANLE":{"clips":504,"clipViews":7620,"hoursLive":109.4},"MARLEA":{"clips":103,"clipViews":5022,"hoursLive":51.7},"DAVIS":{"clips":144,"clipViews":61540,"hoursLive":13.2},"AMBERR":{"clips":955,"clipViews":24858,"hoursLive":97.2},"EDWARD":{"clips":411,"clipViews":8794,"hoursLive":105.1},"LAILAS":{"clips":0,"clipViews":0,"hoursLive":0},"LANIAL":{"clips":811,"clipViews":36713,"hoursLive":24.8},"DCTHAD":{"clips":166,"clipViews":1013,"hoursLive":53},"CATRNA":{"clips":262,"clipViews":63658,"hoursLive":59},"CHAKRA":{"clips":265,"clipViews":3102,"hoursLive":61},"NOTQUI":{"clips":935,"clipViews":79616,"hoursLive":98.1},"RAPHAE":{"clips":916,"clipViews":41068,"hoursLive":91.8},"RIZZ":{"clips":0,"clipViews":0,"hoursLive":0},"RAWDOG":{"clips":494,"clipViews":48314,"hoursLive":98.3},"ARKY":{"clips":951,"clipViews":29516,"hoursLive":40.1},"RYNENZ":{"clips":278,"clipViews":1589,"hoursLive":15.6},"CHICKL":{"clips":151,"clipViews":14570,"hoursLive":4},"MCQN":{"clips":903,"clipViews":26837,"hoursLive":74.8}}